Metadata-Version: 2.1
Name: Mensajes-JavierCh
Version: 6.0
Summary: Un paquete para saludar y despedirse
Home-page: https://www.javchav11.dev
Author: Javier Chávez Hernández
Author-email: javierchavezsw@gmail.com
Classifier: Environment :: Console
Classifier: Intended Audience :: Developers
Classifier: License :: OSI Approved :: MIT License
Classifier: Operating System :: OS Independent
Classifier: Programming Language :: Python
Classifier: Programming Language :: Python :: 3.9
Classifier: Topic :: Utilities
License-File: LICENSE
Requires-Dist: numpy >=2.1.0
